dressup/__init__.py
dressup/__main__.py
dressup/console.py
dressup/converter.py
dressup/exceptions.py
dressup/translator.toml
dressup-0.1.2.dist-info/entry_points.txt
dressup-0.1.2.dist-info/LICENSE
dressup-0.1.2.dist-info/WHEEL
dressup-0.1.2.dist-info/METADATA
dressup-0.1.2.dist-info/RECORD
