Metadata-Version: 2.1
Name: dressup
Version: 0.1.2
Summary: Dress up
Home-page: https://github.com/pscosta5/dressup
License: MIT
Author: Paulo S. Costa
Author-email: Paulo.S.Costa.5@gmail.com
Requires-Python: >=3.8.1,<3.11
Classifier: License :: OSI Approved :: MIT License
Classifier: Programming Language :: Python :: 3
Classifier: Programming Language :: Python :: 3.9
Classifier: Programming Language :: Python :: 3.10
Requires-Dist: colorama (>=0.4.6,<0.5.0)
Requires-Dist: importlib-metadata (>=5.1.0,<6.0.0)
Requires-Dist: rich (>=12.6.0,<13.0.0)
Requires-Dist: toml (>=0.10.2,<0.11.0)
Requires-Dist: typer (>=0.7.0,<0.8.0)
Project-URL: Changelog, https://github.com/pscosta5/dressup/releases
Project-URL: Documentation, https://dressup.readthedocs.io
Project-URL: Repository, https://github.com/pscosta5/dressup
